quoicoubert/__init__.py
quoicoubert-0.0.0.dist-info/METADATA
quoicoubert-0.0.0.dist-info/WHEEL
quoicoubert-0.0.0.dist-info/entry_points.txt
quoicoubert-0.0.0.dist-info/licenses/LICENSE.txt
quoicoubert-0.0.0.dist-info/RECORD
